odoo/addons/web_font_manrope/LICENSE
odoo/addons/web_font_manrope/README.rst
odoo/addons/web_font_manrope/__init__.py
odoo/addons/web_font_manrope/__manifest__.py
odoo/addons/web_font_manrope/images/screen.png
odoo/addons/web_font_manrope/models/__init__.py
odoo/addons/web_font_manrope/models/res_company.py
odoo/addons/web_font_manrope/static/description/icon.png
odoo/addons/web_font_manrope/static/description/index.html
odoo/addons/web_font_manrope/static/fonts/Manrope-Regular.ttf
odoo/addons/web_font_manrope/static/scss/fonts.scss
odoo_addon_web_font_manrope-16.0.1.0.0.dist-info/METADATA
odoo_addon_web_font_manrope-16.0.1.0.0.dist-info/WHEEL
odoo_addon_web_font_manrope-16.0.1.0.0.dist-info/top_level.txt
odoo_addon_web_font_manrope-16.0.1.0.0.dist-info/RECORD
